tkinter_webcam/__init__.py
tkinter_webcam/webcam.py
tkinter_webcam-1.0.9.dist-info/LICENSE
tkinter_webcam-1.0.9.dist-info/METADATA
tkinter_webcam-1.0.9.dist-info/WHEEL
tkinter_webcam-1.0.9.dist-info/top_level.txt
tkinter_webcam-1.0.9.dist-info/RECORD
