Metadata-Version: 2.1
Name: tkinter-webcam
Version: 1.0.9
Summary: Easily display a webcam window in a Tkinter GUI
Home-page: https://github.com/matthewkayne/Tkinter-Webcam
Author: Matthew Kayne
Author-email: matthewkayne2004@gmail.com
License: UNKNOWN
Platform: UNKNOWN
License-File: LICENSE
